irclib/__init__.py
irclib/_version.py
irclib/errors.py
irclib/parser.py
irclib/py.typed
irclib/util/__init__.py
irclib/util/commands.py
irclib/util/compare.py
irclib/util/frozendict.py
irclib/util/numerics.py
irclib/util/string.py
py_irclib-0.8.1.dist-info/METADATA
py_irclib-0.8.1.dist-info/WHEEL
py_irclib-0.8.1.dist-info/licenses/LICENSE
py_irclib-0.8.1.dist-info/RECORD
