Metadata-Version: 2.4
Name: py-irclib
Version: 0.8.1
Summary: A simple library for working with the IRC protocol
Project-URL: Homepage, https://github.com/TotallyNotRobots/py-irclib
Author-email: linuxdaemon <linuxdaemon.irc@gmail.com>
License-Expression: MIT
License-File: LICENSE
Keywords: irc,irc-parser
Classifier: Development Status :: 3 - Alpha
Classifier: License :: OSI Approved :: MIT License
Classifier: Programming Language :: Python :: 3 :: Only
Classifier: Programming Language :: Python :: 3.10
Classifier: Programming Language :: Python :: 3.11
Classifier: Programming Language :: Python :: 3.12
Classifier: Programming Language :: Python :: 3.13
Classifier: Programming Language :: Python :: 3.14
Requires-Python: >=3.10
Requires-Dist: attrs>=20.3.0
Requires-Dist: typing-extensions
